{
    "Master": {
        "Askia Add parameters": [
            {
                "insertsurvey": true,
                "logfile": ".\\logs\\Master_logfile.txt",
                "saveas": "SID.qex",
                "surveypath": ".\\Modules\\Master.qex",
                "updateadp": true,
                "updatemessages": true,
                "usedefaultwhenempty": true
            }
        ],
        "Askia Update parameters": [
            {
                "keepquestions": true,
                "logfile": ".\\logs\\update_IIS_Template_logfile.txt",
                "questionshortcut": "IIS_Template",
                "saveas": "SID.qex",
                "surveypath": ".\\Modules\\Master.qex",
                "updateadp": true,
                "updatemessages": true,
                "updatescreengeneration": true,
                "updatesubsurvey": true,
                "usedefaultwhenempty": true
            },
            {
                "keepquestions": true,
                "logfile": ".\\logs\\update_Presurvey_logfile.txt",
                "questionshortcut": "Presurvey",
                "saveas": "SID.qex",
                "surveypath": ".\\Modules\\Master.qex",
                "updatesubsurvey": true,
                "usedefaultwhenempty": true
            },
            {
                "keepquestions": true,
                "logfile": ".\\logs\\update_Screeners_logfile.txt",
                "questionshortcut": "Screeners",
                "saveas": "SID.qex",
                "surveypath": ".\\Modules\\Master.qex",
                "updatesubsurvey": true,
                "usedefaultwhenempty": true
            },
            {
                "keepquestions": true,
                "logfile": ".\\logs\\update_MainSurvey_logfile.txt",
                "questionshortcut": "MainSurvey",
                "saveas": "SID.qex",
                "surveypath": ".\\Modules\\Master.qex",
                "updatesubsurvey": true,
                "usedefaultwhenempty": true
            },
            {
                "keepquestions": true,
                "logfile": ".\\logs\\update_Demographics_logfile.txt",
                "questionshortcut": "Demographics",
                "saveas": "SID.qex",
                "surveypath": ".\\Modules\\Master.qex",
                "updatesubsurvey": true,
                "usedefaultwhenempty": true
            },
            {
                "keepquestions": true,
                "logfile": ".\\logs\\update_Postsurvey_logfile.txt",
                "questionshortcut": "Postsurvey",
                "saveas": "SID.qex",
                "surveypath": ".\\Modules\\Master.qex",
                "updatesubsurvey": true,
                "usedefaultwhenempty": true
            }
        ],
        "Functionality Group": "Core Askia shell functionalities",
        "Languages": [
            "en-gb",
            "fr-fr",
            "ar-sa",
            "bg-bg",
            "zh-tw",
            "cs-cz",
            "da-dk",
            "de-de",
            "el-gr",
            "en-us",
            "fi-fi",
            "he-il",
            "hu-hu",
            "it-it",
            "ja-jp",
            "ko-kr",
            "nl-nl",
            "nb-no",
            "pl-pl",
            "pt-br",
            "ro-ro",
            "ru-ru",
            "hr-hr",
            "sk-sk",
            "sv-se",
            "th-th",
            "tr-tr",
            "ur-pk",
            "id-id",
            "uk-ua",
            "sl-si",
            "et-ee",
            "lv-lv",
            "lt-lt",
            "vi-vn",
            "lt-az-az",
            "af-za",
            "hi-in",
            "ms-my",
            "kk-kz",
            "sw-ke",
            "ta-in",
            "mn-mn",
            "lo-la",
            "ne-np",
            "ps-af",
            "No_CI_15",
            "yo-ng",
            "ba-ru",
            "br-fr",
            "co-fr",
            "ar-iq",
            "zh-cn",
            "de-ch",
            "es-mx",
            "fr-be",
            "it-ch",
            "nl-be",
            "nn-no",
            "pt-pt",
            "ar-eg",
            "zh-hk",
            "de-at",
            "en-au",
            "No_CI_70",
            "fr-ca",
            "zh-sg",
            "en-ca",
            "es-gt",
            "fr-ch",
            "zh-mo",
            "en-nz",
            "es-cr",
            "ar-ma",
            "es-pa",
            "fr-mc",
            "en-za",
            "es-do",
            "en-jm",
            "es-ve",
            "en-cb",
            "es-co",
            "sr-rs",
            "en-bz",
            "es-pe",
            "ar-jo",
            "en-tt",
            "es-ar",
            "ar-lb",
            "en-zw",
            "es-ec",
            "ar-kw",
            "en-ph",
            "es-cl",
            "ar-ae",
            "es-uy",
            "es-py",
            "ar-qa",
            "en-in",
            "es-bo",
            "en-my",
            "es-sv",
            "en-sg",
            "es-hn",
            "es-ni",
            "es-pr",
            "es-us",
            "No_CI_21",
            "No_CI_13"
        ],
        "Resources": [
            {
                "Name": "IIS_Fish.adp",
                "Version": "1.0.1"
            }
        ],
        "Version": "1.0.3",
        "dependencies": [],
        "hidden": true,
        "merge order": 0,
        "qex name": "Master"
    }
}